odoo/addons/hr_expense_payment_widget_amount/README.rst
odoo/addons/hr_expense_payment_widget_amount/__init__.py
odoo/addons/hr_expense_payment_widget_amount/__manifest__.py
odoo/addons/hr_expense_payment_widget_amount/i18n/hr_expense_payment_widget_amount.pot
odoo/addons/hr_expense_payment_widget_amount/i18n/it.po
odoo/addons/hr_expense_payment_widget_amount/models/__init__.py
odoo/addons/hr_expense_payment_widget_amount/models/account_move.py
odoo/addons/hr_expense_payment_widget_amount/models/hr_expense_sheet.py
odoo/addons/hr_expense_payment_widget_amount/readme/CONTRIBUTORS.rst
odoo/addons/hr_expense_payment_widget_amount/readme/DESCRIPTION.rst
odoo/addons/hr_expense_payment_widget_amount/static/description/icon.png
odoo/addons/hr_expense_payment_widget_amount/static/description/index.html
odoo/addons/hr_expense_payment_widget_amount/tests/__init__.py
odoo/addons/hr_expense_payment_widget_amount/tests/test_hr_expense_payment_widget_amount.py
odoo/addons/hr_expense_payment_widget_amount/views/hr_expense_views.xml
odoo_addon_hr_expense_payment_widget_amount-15.0.1.0.1.dist-info/METADATA
odoo_addon_hr_expense_payment_widget_amount-15.0.1.0.1.dist-info/WHEEL
odoo_addon_hr_expense_payment_widget_amount-15.0.1.0.1.dist-info/top_level.txt
odoo_addon_hr_expense_payment_widget_amount-15.0.1.0.1.dist-info/RECORD
